README.md
setup.py
irtools/__init__.py
irtools/environment.py
irtools/utils.py
irtools/_libs/__init__.py
irtools/_libs/byte_utils.py
irtools/_libs/collection_utils.py
irtools/_libs/csv_utils.py
irtools/_libs/datetime_utils.py
irtools/_libs/decorator_utils.py
irtools/_libs/docker_utils.py
irtools/_libs/enum_utils.py
irtools/_libs/env_utils.py
irtools/_libs/exec_utils.py
irtools/_libs/file_utils.py
irtools/_libs/func_utils.py
irtools/_libs/linux_utils.py
irtools/_libs/log_utils.py
irtools/_libs/mail_utils.py
irtools/_libs/package_utils.py
irtools/_libs/proc_utils.py
irtools/_libs/report_utils.py
irtools/_libs/service_utils.py
irtools/_libs/sort_utils.py
irtools/_libs/ssh_utils.py
irtools/_libs/string_utils.py
irtools/_libs/wait_utils.py
irtools/_libs/tests/__init__.py
irtools/_libs/tests/test_exec_utils.py
irtools/_libs/tests/test_file_utils.py
irtools/_libs/tests/test_func_utils.py
irtools/_libs/tests/test_wait_utils.py
irtools/kits/__init__.py
irtools/kits/json_structure.py
irtools/kits/mailer.py
irtools/kits/restful_api.py
irtools/kits/taskmanager.py
irtools/kits/thread_pool.py
irtools/kits/virtual_interface.py
irtools/tests/__init__.py
irtools/tests/test_json_structure.py
irtools/tests/test_taskmanager.py
irtools/tests/test_thread_pool.py
py_irtools.egg-info/PKG-INFO
py_irtools.egg-info/SOURCES.txt
py_irtools.egg-info/dependency_links.txt
py_irtools.egg-info/requires.txt
py_irtools.egg-info/top_level.txt