Metadata-Version: 2.1
Name: py-irtools
Version: 1.0.7
Summary: A package with useful tools
Home-page: https://github.com/InbarRose/irtools
Author: Inbar Rose
Author-email: inbar.rose1@gmail.com
License: UNKNOWN
Platform: UNKNOWN
Classifier: Programming Language :: Python :: 2.7
Classifier: License :: OSI Approved :: MIT License
Classifier: Operating System :: OS Independent
